{"version":2,"kind":"Notebook","sha256":"c52c9d112415f04159b5924a06962f93bf3b5247c8998a26fdd22fc0f3294570","slug":"notebooks.foundation.mhw-observation-myst","location":"/notebooks/foundation/mhw_observation_myst.ipynb","dependencies":[],"frontmatter":{"title":"Marine Heatwave Detection","content_includes_title":true,"kernelspec":{"name":"python3","display_name":"Python 3 (ipykernel)","language":"python"},"authors":[{"nameParsed":{"literal":"Chia-Wei Hsu","given":"Chia-Wei","family":"Hsu"},"name":"Chia-Wei Hsu","id":"contributors-myst-generated-uid-0"}],"open_access":true,"license":{"content":{"id":"CC-BY-4.0","url":"https://creativecommons.org/licenses/by/4.0/","name":"Creative Commons Attribution 4.0 International","free":true,"CC":true},"code":{"id":"Apache-2.0","url":"https://opensource.org/licenses/Apache-2.0","name":"Apache License 2.0","free":true,"osi":true}},"github":"https://github.com/projectpythia/marine-heatwave-cookbook","copyright":"2024","affiliations":[{"id":"UAlbany","name":"University at Albany (SUNY)","department":"Atmospheric and Environmental Sciences","url":"https://www.albany.edu/daes"},{"id":"CISL","name":"NSF National Center for Atmospheric Research","department":"Computational and Information Systems Lab","url":"https://www.cisl.ucar.edu"},{"id":"Unidata","name":"NSF Unidata","url":"https://www.unidata.ucar.edu"},{"id":"Argonne","name":"Argonne National Laboratory","department":"Environmental Science Division","url":"https://www.anl.gov/evs"},{"id":"CarbonPlan","name":"CarbonPlan","url":"https://carbonplan.org"},{"id":"NVIDIA","name":"NVIDIA Corporation","url":"https://www.nvidia.com/"}],"numbering":{"title":{"offset":1}},"edit_url":"https://github.com/projectpythia/marine-heatwave-cookbook/blob/main/notebooks/foundation/mhw_observation_myst.ipynb","thumbnail":"/marine-heatwave-cookbook/build/MHW_logo-eb04466d21ce962e22d4498e48f35a6a.png","exports":[{"format":"ipynb","filename":"mhw_observation_myst.ipynb","url":"/marine-heatwave-cookbook/build/mhw_observation_myst-4b1e1c87c77b5ce4c66bd7076a65336c.ipynb"}]},"widgets":{},"mdast":{"type":"root","children":[{"type":"block","kind":"notebook-content","data":{"tags":[]},"children":[{"type":"paragraph","position":{"start":{"line":1,"column":1},"end":{"line":1,"column":1}},"children":[{"type":"image","url":"/marine-heatwave-cookbook/build/MHW_logo-eb04466d21ce962e22d4498e48f35a6a.png","alt":"MHW Logo","width":250,"key":"AmCdo6JgNz","urlSource":"../../MHW_logo.png"}],"key":"PHxgQQeiDt"}],"visibility":"show","key":"LddhohQqRV"},{"type":"block","kind":"notebook-content","children":[{"type":"heading","depth":1,"position":{"start":{"line":1,"column":1},"end":{"line":1,"column":1}},"children":[{"type":"text","value":"Marine Heatwave Detection","position":{"start":{"line":1,"column":1},"end":{"line":1,"column":1}},"key":"KvpOzmCznu"}],"identifier":"marine-heatwave-detection","label":"Marine Heatwave Detection","html_id":"marine-heatwave-detection","implicit":true,"key":"fOL5Yv41xs"},{"type":"paragraph","position":{"start":{"line":2,"column":1},"end":{"line":4,"column":1}},"children":[{"type":"text","value":"Marine heatwaves are periods of persistent anomalously warm ocean temperatures, which can have significant impacts on marine life as well as coastal communities and economies.\nTo detect the warm ocean water, sea surface temperature (SST) is usually used to define if there is any marine heatwave event.\nThe following example is following the paper ","position":{"start":{"line":2,"column":1},"end":{"line":2,"column":1}},"key":"Gaq4kJKQ6v"},{"type":"cite","url":"http://doi.org/10.1038/s41586-022-04573-9","position":{"start":{"line":2,"column":1},"end":{"line":2,"column":1}},"children":[{"type":"text","value":"Jacox et al., 2022","position":{"start":{"line":2,"column":1},"end":{"line":2,"column":1}},"key":"Ib5CiTS8rg"}],"kind":"narrative","label":"Jacox_2022","identifier":"http://doi.org/10.1038/s41586-022-04573-9","enumerator":"1","key":"XIc2JYM5VH"}],"key":"Zk6TZKIQjl"}],"key":"LsTp7UHS8x"},{"type":"block","kind":"notebook-content","children":[{"type":"thematicBreak","position":{"start":{"line":1,"column":1},"end":{"line":1,"column":1}},"key":"BNYANw53va"}],"key":"QlWhdjlYT9"},{"type":"block","kind":"notebook-content","children":[{"type":"heading","depth":2,"position":{"start":{"line":1,"column":1},"end":{"line":1,"column":1}},"children":[{"type":"text","value":"Overview","position":{"start":{"line":1,"column":1},"end":{"line":1,"column":1}},"key":"OHFiBANrGf"}],"identifier":"overview","label":"Overview","html_id":"overview","implicit":true,"key":"hrrwRMdWxH"},{"type":"paragraph","position":{"start":{"line":3,"column":1},"end":{"line":3,"column":1}},"children":[{"type":"text","value":"In this page/notebook, we will be go throught the following steps","position":{"start":{"line":3,"column":1},"end":{"line":3,"column":1}},"key":"IyITrbtfqC"}],"key":"C0qtGx7Z6F"},{"type":"list","ordered":true,"start":1,"spread":false,"position":{"start":{"line":5,"column":1},"end":{"line":9,"column":1}},"children":[{"type":"listItem","spread":true,"position":{"start":{"line":5,"column":1},"end":{"line":5,"column":1}},"children":[{"type":"text","value":"Extract the data from the PSL OPeNDAP server","position":{"start":{"line":5,"column":1},"end":{"line":5,"column":1}},"key":"rbeR6TfTxr"}],"key":"c62LLN5ggZ"},{"type":"listItem","spread":true,"position":{"start":{"line":6,"column":1},"end":{"line":6,"column":1}},"children":[{"type":"text","value":"Calculate the SST climatology","position":{"start":{"line":6,"column":1},"end":{"line":6,"column":1}},"key":"FaQMi0RclK"}],"key":"coAfW7w95E"},{"type":"listItem","spread":true,"position":{"start":{"line":7,"column":1},"end":{"line":7,"column":1}},"children":[{"type":"text","value":"Calculate the SST anomaly","position":{"start":{"line":7,"column":1},"end":{"line":7,"column":1}},"key":"WsB8BpfLJJ"}],"key":"vmw9xKOio8"},{"type":"listItem","spread":true,"position":{"start":{"line":8,"column":1},"end":{"line":8,"column":1}},"children":[{"type":"text","value":"Determine the SST threshold based on the anomaly","position":{"start":{"line":8,"column":1},"end":{"line":8,"column":1}},"key":"w6Z5FWV8GB"}],"key":"uhyr3CoMml"},{"type":"listItem","spread":true,"position":{"start":{"line":9,"column":1},"end":{"line":9,"column":1}},"children":[{"type":"text","value":"Identify the marine heatwaves based on threshold","position":{"start":{"line":9,"column":1},"end":{"line":9,"column":1}},"key":"znYwD1VEnQ"}],"key":"i3U5S6XvsD"}],"key":"SaRNagfuPr"}],"key":"VXeVCVJqec"},{"type":"block","kind":"notebook-content","children":[{"type":"heading","depth":2,"position":{"start":{"line":1,"column":1},"end":{"line":1,"column":1}},"children":[{"type":"text","value":"Prerequisites","position":{"start":{"line":1,"column":1},"end":{"line":1,"column":1}},"key":"r3Usqjixs4"}],"identifier":"prerequisites","label":"Prerequisites","html_id":"prerequisites","implicit":true,"key":"i9Ae21Lkf4"},{"type":"paragraph","position":{"start":{"line":3,"column":1},"end":{"line":3,"column":1}},"children":[{"type":"text","value":"To better understand and follow the steps in the notebook, it will be helpful for user to go through","position":{"start":{"line":3,"column":1},"end":{"line":3,"column":1}},"key":"KIiEAZLpqX"}],"key":"mRcTvKTt0D"},{"type":"table","position":{"start":{"line":5,"column":1},"end":{"line":7,"column":1}},"children":[{"type":"tableRow","position":{"start":{"line":5,"column":1},"end":{"line":5,"column":1}},"children":[{"type":"tableCell","header":true,"position":{"start":{"line":5,"column":1},"end":{"line":5,"column":1}},"children":[{"type":"text","value":"Concepts","position":{"start":{"line":5,"column":1},"end":{"line":5,"column":1}},"key":"OCMu1mH9PG"}],"key":"CbRy6cSuW6"},{"type":"tableCell","header":true,"position":{"start":{"line":5,"column":1},"end":{"line":5,"column":1}},"children":[{"type":"text","value":"Importance","position":{"start":{"line":5,"column":1},"end":{"line":5,"column":1}},"key":"fazPZujsR8"}],"key":"qKFvLW50n7"},{"type":"tableCell","header":true,"position":{"start":{"line":5,"column":1},"end":{"line":5,"column":1}},"children":[{"type":"text","value":"Notes","position":{"start":{"line":5,"column":1},"end":{"line":5,"column":1}},"key":"GS6z0tjb8L"}],"key":"KDX65CWfcn"}],"key":"SwDnTaIWjc"},{"type":"tableRow","position":{"start":{"line":7,"column":1},"end":{"line":7,"column":1}},"children":[{"type":"tableCell","position":{"start":{"line":7,"column":1},"end":{"line":7,"column":1}},"children":[{"type":"link","url":"https://foundations.projectpythia.org/core/xarray.html","position":{"start":{"line":7,"column":1},"end":{"line":7,"column":1}},"children":[{"type":"text","value":"Xarray","position":{"start":{"line":7,"column":1},"end":{"line":7,"column":1}},"key":"YeGrbZRfkS"}],"urlSource":"https://foundations.projectpythia.org/core/xarray.html","key":"hjyFzifRZG"}],"key":"jQda345hHk"},{"type":"tableCell","position":{"start":{"line":7,"column":1},"end":{"line":7,"column":1}},"children":[{"type":"text","value":"Helpful","position":{"start":{"line":7,"column":1},"end":{"line":7,"column":1}},"key":"AXYpx1SKTD"}],"key":"msfEVwgZH4"},{"type":"tableCell","position":{"start":{"line":7,"column":1},"end":{"line":7,"column":1}},"children":[{"type":"text","value":"Chunking and OPeNDAP access","position":{"start":{"line":7,"column":1},"end":{"line":7,"column":1}},"key":"egX1VJCGuc"}],"key":"b1IhCfS12X"}],"key":"vSsHvlccYA"}],"key":"YOQtNcbGZ2"},{"type":"list","ordered":false,"spread":false,"position":{"start":{"line":9,"column":1},"end":{"line":16,"column":1}},"children":[{"type":"listItem","spread":true,"position":{"start":{"line":9,"column":1},"end":{"line":9,"column":1}},"children":[{"type":"strong","position":{"start":{"line":9,"column":1},"end":{"line":9,"column":1}},"children":[{"type":"text","value":"Time to learn","position":{"start":{"line":9,"column":1},"end":{"line":9,"column":1}},"key":"FkkSr1VPmG"}],"key":"GkZSqU91UT"},{"type":"text","value":": 15 minutes.","position":{"start":{"line":9,"column":1},"end":{"line":9,"column":1}},"key":"MKDWNPebHV"}],"key":"dFIzznTYkL"},{"type":"listItem","spread":true,"position":{"start":{"line":10,"column":1},"end":{"line":16,"column":1}},"children":[{"type":"strong","position":{"start":{"line":10,"column":1},"end":{"line":10,"column":1}},"children":[{"type":"text","value":"System requirements","position":{"start":{"line":10,"column":1},"end":{"line":10,"column":1}},"key":"oOXw9Mqa6R"}],"key":"dSisMVkdto"},{"type":"text","value":":","position":{"start":{"line":10,"column":1},"end":{"line":10,"column":1}},"key":"qMuCUOSHMQ"},{"type":"list","ordered":false,"spread":false,"position":{"start":{"line":11,"column":1},"end":{"line":16,"column":1}},"children":[{"type":"listItem","spread":true,"position":{"start":{"line":11,"column":1},"end":{"line":11,"column":1}},"children":[{"type":"text","value":"python","position":{"start":{"line":11,"column":1},"end":{"line":11,"column":1}},"key":"HcLM69I1uC"}],"key":"CExlU4BBwS"},{"type":"listItem","spread":true,"position":{"start":{"line":12,"column":1},"end":{"line":12,"column":1}},"children":[{"type":"text","value":"Xarray","position":{"start":{"line":12,"column":1},"end":{"line":12,"column":1}},"key":"koMAhWrUoQ"}],"key":"xyyQ5WhuFq"},{"type":"listItem","spread":true,"position":{"start":{"line":13,"column":1},"end":{"line":13,"column":1}},"children":[{"type":"text","value":"pydap (not imported but will be used in the Xarray backend)","position":{"start":{"line":13,"column":1},"end":{"line":13,"column":1}},"key":"uE6qEkry3N"}],"key":"kmKZGaGp6W"},{"type":"listItem","spread":true,"position":{"start":{"line":14,"column":1},"end":{"line":14,"column":1}},"children":[{"type":"text","value":"matplotlib (not imported but will be used in the Xarray plotting)","position":{"start":{"line":14,"column":1},"end":{"line":14,"column":1}},"key":"EI2Teqf1Qq"}],"key":"L6pIqfTjyk"},{"type":"listItem","spread":true,"position":{"start":{"line":15,"column":1},"end":{"line":15,"column":1}},"children":[{"type":"text","value":"Numpy","position":{"start":{"line":15,"column":1},"end":{"line":15,"column":1}},"key":"TkASAjuJm1"}],"key":"H9IfaPqRJZ"},{"type":"listItem","spread":true,"position":{"start":{"line":16,"column":1},"end":{"line":16,"column":1}},"children":[{"type":"text","value":"plotly (only for the final interactive plot)","position":{"start":{"line":16,"column":1},"end":{"line":16,"column":1}},"key":"oPHQNFtdnK"}],"key":"TffKN3j1Z4"}],"key":"FRmkerD0pM"}],"key":"ZZzFz2GtOb"}],"key":"lnlJ4UMYN9"}],"key":"S6W3KAfgVY"},{"type":"block","kind":"notebook-content","children":[{"type":"thematicBreak","position":{"start":{"line":1,"column":1},"end":{"line":1,"column":1}},"key":"drgY9iidou"}],"key":"GvL7nVXUUd"},{"type":"block","kind":"notebook-content","children":[{"type":"heading","depth":2,"position":{"start":{"line":1,"column":1},"end":{"line":1,"column":1}},"children":[{"type":"text","value":"Imports","position":{"start":{"line":1,"column":1},"end":{"line":1,"column":1}},"key":"jKvoXjyJz5"}],"identifier":"imports","label":"Imports","html_id":"imports","implicit":true,"key":"Q2UDqQlavZ"}],"key":"ZvrK9eFQVV"},{"type":"block","kind":"notebook-code","data":{"tags":[]},"children":[{"type":"code","lang":"python","executable":true,"value":"# import the needed packages\nimport warnings\nimport xarray as xr\nimport numpy as np\nimport plotly.express as px","visibility":"show","key":"G461RthQmi"},{"type":"output","id":"xl4deETaEc9St2bhXHBog","data":[],"visibility":"show","key":"KPF8bhplQx"}],"visibility":"show","key":"rd0nr36Bq1"},{"type":"block","kind":"notebook-code","children":[{"type":"code","lang":"python","executable":true,"value":"warnings.simplefilter(\"ignore\")","key":"Bwd1sNh33H"},{"type":"output","id":"PAuB1Cve3KOAHJgDgBv0r","data":[],"key":"qcuPzKPYJk"}],"key":"MtV2mx9Y5W"},{"type":"block","kind":"notebook-content","children":[{"type":"div","class":"admonition alert alert-info","children":[{"type":"paragraph","children":[{"type":"text","value":"warnings.simplefilter","key":"hc5MXbkwfO"}],"key":"VYimuyxWMq"},{"type":"text","value":"This line of code is not affecting the execution but just removing some of the warning output that might clutter your notebook. However, do pay attention to some of the warnings since they will indicate some deprecation of function or arg/kwarg in future update.","key":"AD883Sp83K"}],"key":"Km7r2tFh6O"}],"key":"XQ59GVkKkI"},{"type":"block","kind":"notebook-content","children":[{"type":"heading","depth":2,"position":{"start":{"line":1,"column":1},"end":{"line":1,"column":1}},"children":[{"type":"text","value":"Extract the data from an OPeNDAP server","position":{"start":{"line":1,"column":1},"end":{"line":1,"column":1}},"key":"ZNCxBHfRR3"}],"identifier":"extract-the-data-from-an-opendap-server","label":"Extract the data from an OPeNDAP server","html_id":"extract-the-data-from-an-opendap-server","implicit":true,"key":"KVGoYztZ3B"},{"type":"paragraph","position":{"start":{"line":3,"column":1},"end":{"line":4,"column":1}},"children":[{"type":"text","value":"In this page/notebook, we demonstrate how to use the ","position":{"start":{"line":3,"column":1},"end":{"line":3,"column":1}},"key":"wVUd7YYoFd"},{"type":"link","url":"https://psl.noaa.gov/data/gridded/data.noaa.oisst.v2.highres.html","position":{"start":{"line":3,"column":1},"end":{"line":3,"column":1}},"children":[{"type":"text","value":"NOAA OISST v2 High-resolution dataset","position":{"start":{"line":3,"column":1},"end":{"line":3,"column":1}},"key":"KtrW6eFOgk"}],"urlSource":"https://psl.noaa.gov/data/gridded/data.noaa.oisst.v2.highres.html","key":"j2eaXC3Ekj"},{"type":"text","value":" to detect marine heatwaves.\nThe dataset is currently hosted by ","position":{"start":{"line":3,"column":1},"end":{"line":3,"column":1}},"key":"wOiVvwagym"},{"type":"link","url":"https://psl.noaa.gov/data/gridded","position":{"start":{"line":3,"column":1},"end":{"line":3,"column":1}},"children":[{"type":"text","value":"NOAA Physical Sciences Laboratory","position":{"start":{"line":3,"column":1},"end":{"line":3,"column":1}},"key":"ejNjEawGbV"}],"urlSource":"https://psl.noaa.gov/data/gridded","key":"reSwGfl71k"},{"type":"text","value":".","position":{"start":{"line":3,"column":1},"end":{"line":3,"column":1}},"key":"tMPqOIhkEI"}],"key":"n2dZhazsUa"},{"type":"div","class":"admonition alert alert-info","children":[{"type":"paragraph","children":[{"type":"text","value":"Info","key":"IZs6mkpq5t"}],"key":"dDYZ6JKChf"},{"type":"text","value":"To explore more gridded datasets that are hosted at NOAA PSL, here is a useful ","key":"znASjJF9en"},{"type":"link","url":"https://psl.noaa.gov/data/gridded/index.html","children":[{"type":"text","value":"search tool","key":"VmteWnKRcm"}],"urlSource":"https://psl.noaa.gov/data/gridded/index.html","key":"vEQZyDplJ9"}],"key":"tdedKKMsAG"}],"key":"lIRnV3o35A"},{"type":"block","kind":"notebook-code","data":{"tags":[]},"children":[{"type":"code","lang":"python","executable":true,"value":"opendap_mon_url = \"https://psl.noaa.gov/thredds/dodsC/Datasets/noaa.oisst.v2.highres/sst.mon.mean.nc\"","visibility":"show","key":"ZGkjYWH1LM"},{"type":"output","id":"akHp_nfhRY5J_86N-SV4B","data":[],"visibility":"show","key":"HL87ZBMQrb"}],"visibility":"show","key":"oWFRx1Nfrh"},{"type":"block","kind":"notebook-content","children":[{"type":"heading","depth":3,"position":{"start":{"line":1,"column":1},"end":{"line":1,"column":1}},"children":[{"type":"text","value":"Xarray getting remote data","position":{"start":{"line":1,"column":1},"end":{"line":1,"column":1}},"key":"lEPoMHuALR"}],"identifier":"xarray-getting-remote-data","label":"Xarray getting remote data","html_id":"xarray-getting-remote-data","implicit":true,"key":"v8nqsmZMKJ"},{"type":"paragraph","position":{"start":{"line":3,"column":1},"end":{"line":5,"column":1}},"children":[{"type":"text","value":"Xarray has a great support on accessing data in the cloud.\nIt has been continue to expend its capability and functionality with the community discussion like ","position":{"start":{"line":3,"column":1},"end":{"line":3,"column":1}},"key":"AGHJypKiAk"},{"type":"link","url":"https://github.com/pydata/xarray/issues/1068","position":{"start":{"line":3,"column":1},"end":{"line":3,"column":1}},"children":[{"type":"text","value":"this","position":{"start":{"line":3,"column":1},"end":{"line":3,"column":1}},"key":"FUBFpOuGCf"}],"urlSource":"https://github.com/pydata/xarray/issues/1068","data":{"kind":"issue","org":"pydata","repo":"xarray","issue_number":"1068"},"internal":false,"protocol":"github","key":"mTvQlRvYGZ"},{"type":"text","value":".\nHere we use the ","position":{"start":{"line":3,"column":1},"end":{"line":3,"column":1}},"key":"P02KtCa4hi"},{"type":"inlineCode","value":"xr.open_dataset","position":{"start":{"line":3,"column":1},"end":{"line":3,"column":1}},"key":"OgENFOSODc"},{"type":"text","value":" method with the keyword argument (","position":{"start":{"line":3,"column":1},"end":{"line":3,"column":1}},"key":"DNJ8h7rC9D"},{"type":"inlineCode","value":"engine='pydap'","position":{"start":{"line":3,"column":1},"end":{"line":3,"column":1}},"key":"hANiO6NXDV"},{"type":"text","value":") to use the pydap package in the backend to access the OPeNDAP server.","position":{"start":{"line":3,"column":1},"end":{"line":3,"column":1}},"key":"D5KZjutVKm"}],"key":"UZjOH80Oqg"}],"key":"rnRNK0E40H"},{"type":"block","kind":"notebook-code","data":{"tags":[]},"children":[{"type":"code","lang":"python","executable":true,"value":"ds_mon = xr.open_dataset(opendap_mon_url, engine='pydap', chunks={'time':12,'lon':-1,'lat':-1})","visibility":"show","key":"rsiMffi2DO"},{"type":"output","id":"cwPF0cl8XfmLCqvQpJoXP","data":[],"visibility":"show","key":"BAKgw2F0Sn"}],"visibility":"show","key":"iHpwUAUC38"},{"type":"block","kind":"notebook-content","children":[{"type":"div","class":"admonition alert alert-success","children":[{"type":"paragraph","children":[{"type":"text","value":"Lazy Loading","key":"KME6FUinHp"}],"key":"GJsqs8ok0s"},{"type":"text","value":"We can load the data lazily (only loading the metadata and coordinates information) and peek at the data's dimension and availability on our local machine. The actual data (SST values at each grid point in this case) will only be downloaded from the PSL server when further data manipulation (subsetting and aggregation like calculating mean) is needed. The only thing user needs to do to activate this function is to read the netCDF file using the `xr.open_dataset()` method with the keyword argument `chunks={'time':12,'lon':-1,'lat':-1}` provided. The chunk reading approach provide the opportunity to reduce the memory usage on the local machine during the calculation, the possibility of parallelizing the processes, and side-stepping the data download limit set by the OPeNDAP server (PSL server has a 500MB limit). The dataset is loaded lazily (only metadata and coordinates) shown below.","key":"SyLaIOhsnk"}],"key":"G9XAWk1Osp"},{"type":"paragraph","position":{"start":{"line":14,"column":1},"end":{"line":15,"column":1}},"children":[{"type":"text","value":"In our example, we set the size of each chunk to be 12(time)x1440(lon)x720(lat) (when setting the chunk size = -1, it will use the length of the dimension as the chunksize) which is equal to 47.46 MB of data while the entire dataset is 1.39 GB.\nThis allows us to get data in 47.46 MB chunk per download request.","position":{"start":{"line":14,"column":1},"end":{"line":14,"column":1}},"key":"CiGaYGUzI0"}],"key":"CjMOq1dV7v"},{"type":"paragraph","position":{"start":{"line":17,"column":1},"end":{"line":17,"column":1}},"children":[{"type":"text","value":"The dataset is loaded lazily (only metadata and coordinates) shown below.","position":{"start":{"line":17,"column":1},"end":{"line":17,"column":1}},"key":"QQxghcaBBr"}],"key":"DDL7dn7GN2"}],"key":"rZ0FnlrgXT"},{"type":"block","kind":"notebook-code","data":{"tags":[]},"children":[{"type":"code","lang":"python","executable":true,"value":"ds_mon","visibility":"show","key":"yweZsz2te7"},{"type":"output","id":"E3-taXA4efFgdKhXih3mO","data":[{"output_type":"execute_result","execution_count":5,"metadata":{},"data":{"text/plain":{"content":"<xarray.Dataset> Size: 2GB\nDimensions:  (time: 527, lat: 720, lon: 1440)\nCoordinates:\n  * time     (time) datetime64[ns] 4kB 1981-09-01 1981-10-01 ... 2025-07-01\n  * lat      (lat) float32 3kB -89.88 -89.62 -89.38 -89.12 ... 89.38 89.62 89.88\n  * lon      (lon) float32 6kB 0.125 0.375 0.625 0.875 ... 359.4 359.6 359.9\nData variables:\n    sst      (time, lat, lon) float32 2GB dask.array<chunksize=(12, 720, 1440), meta=np.ndarray>\nAttributes:\n    Conventions:          CF-1.5\n    title:                NOAA/NCEI 1/4 Degree Daily Optimum Interpolation Se...\n    institution:          NOAA/National Centers for Environmental Information\n    source:               NOAA/NCEI https://www.ncei.noaa.gov/data/sea-surfac...\n    References:           https://www.psl.noaa.gov/data/gridded/data.noaa.ois...\n    dataset_title:        NOAA Daily Optimum Interpolation Sea Surface Temper...\n    version:              Version 2.1\n    comment:              Reynolds, et al.(2007) Daily High-Resolution-Blende...\n    _NCProperties:        version=2,netcdf=4.7.0,hdf5=1.10.5,\n    Unlimited_Dimension:  time","content_type":"text/plain"},"text/html":{"content_type":"text/html","hash":"aa37ada980e3eafe76a7a6df2e9cd739","path":"/marine-heatwave-cookbook/build/aa37ada980e3eafe76a7a6df2e9cd739.html"}}}],"visibility":"show","key":"yy4H3wkNBE"}],"visibility":"show","key":"ZFffsNSXwk"},{"type":"block","kind":"notebook-content","children":[{"type":"heading","depth":2,"position":{"start":{"line":1,"column":1},"end":{"line":1,"column":1}},"children":[{"type":"text","value":"Calculate the SST climatology","position":{"start":{"line":1,"column":1},"end":{"line":1,"column":1}},"key":"Exqs5Iw7QP"}],"identifier":"calculate-the-sst-climatology","label":"Calculate the SST climatology","html_id":"calculate-the-sst-climatology","implicit":true,"key":"FQrjvnJKR2"},{"type":"paragraph","position":{"start":{"line":2,"column":1},"end":{"line":3,"column":1}},"children":[{"type":"text","value":"First, we need to define the period that we are going to use to calculate the climatology.\nHere, we picked the 2019-2020 period to calculate the climatology.","position":{"start":{"line":2,"column":1},"end":{"line":2,"column":1}},"key":"PAqciGu4RX"}],"key":"VmcoefyVVC"},{"type":"div","class":"admonition alert alert-warning","children":[{"type":"paragraph","children":[{"type":"text","value":"Climatology","key":"Qf1sh8t5aC"}],"key":"oc2rfAUrAm"},{"type":"text","value":"For a more accurate and scientifically valid estimate of marine heatwaves, one should usually consider a climatology period of at least 30 years. Here we set the climatology period from 2019 to 2020 (2 years) to speed up the processing time and for demonstration only. The shorter period (less memory consumption) also makes the interactive notebook launch on this page available for the user to manipulate and play with the dataset.","key":"w0fPN1OUxC"}],"key":"lLto7ClcxI"}],"key":"Xt38ITCE4s"},{"type":"block","kind":"notebook-code","data":{"tags":[]},"children":[{"type":"code","lang":"python","executable":true,"value":"climo_start_yr = 2019             # determine the climatology/linear trend start year\nclimo_end_yr = 2020               # determine the climatology/linear trend end year\n\nds_mon_crop = ds_mon.where((ds_mon['time.year']>=climo_start_yr)&\n                           (ds_mon['time.year']<=climo_end_yr),drop=True)","visibility":"show","key":"JW4Gclgb8a"},{"type":"output","id":"3iv7_APiv1poQfzHGAdmS","data":[],"visibility":"show","key":"BX6wYfHB4Y"}],"visibility":"show","key":"BxE10Icppc"},{"type":"block","kind":"notebook-code","data":{"tags":[]},"children":[{"type":"code","lang":"python","executable":true,"value":"ds_mon_crop","visibility":"show","key":"fqnzjSW1lf"},{"type":"output","id":"w4JVJojiO0APp1sM17xRF","data":[{"output_type":"execute_result","execution_count":7,"metadata":{},"data":{"text/plain":{"content":"<xarray.Dataset> Size: 100MB\nDimensions:  (time: 24, lat: 720, lon: 1440)\nCoordinates:\n  * time     (time) datetime64[ns] 192B 2019-01-01 2019-02-01 ... 2020-12-01\n  * lat      (lat) float32 3kB -89.88 -89.62 -89.38 -89.12 ... 89.38 89.62 89.88\n  * lon      (lon) float32 6kB 0.125 0.375 0.625 0.875 ... 359.4 359.6 359.9\nData variables:\n    sst      (time, lat, lon) float32 100MB dask.array<chunksize=(11, 720, 1440), meta=np.ndarray>\nAttributes:\n    Conventions:          CF-1.5\n    title:                NOAA/NCEI 1/4 Degree Daily Optimum Interpolation Se...\n    institution:          NOAA/National Centers for Environmental Information\n    source:               NOAA/NCEI https://www.ncei.noaa.gov/data/sea-surfac...\n    References:           https://www.psl.noaa.gov/data/gridded/data.noaa.ois...\n    dataset_title:        NOAA Daily Optimum Interpolation Sea Surface Temper...\n    version:              Version 2.1\n    comment:              Reynolds, et al.(2007) Daily High-Resolution-Blende...\n    _NCProperties:        version=2,netcdf=4.7.0,hdf5=1.10.5,\n    Unlimited_Dimension:  time","content_type":"text/plain"},"text/html":{"content_type":"text/html","hash":"217eb454e1cf84cb4114c12f0c5e6ec2","path":"/marine-heatwave-cookbook/build/217eb454e1cf84cb4114c12f0c5e6ec2.html"}}}],"visibility":"show","key":"Zv7pmg4JM1"}],"visibility":"show","key":"kyQpfJz5MW"},{"type":"block","kind":"notebook-content","children":[{"type":"paragraph","position":{"start":{"line":1,"column":1},"end":{"line":1,"column":1}},"children":[{"type":"text","value":"To calculate the SST monthly climatology, we utilize the ","position":{"start":{"line":1,"column":1},"end":{"line":1,"column":1}},"key":"qrMdChzY7R"},{"type":"inlineCode","value":"groupby","position":{"start":{"line":1,"column":1},"end":{"line":1,"column":1}},"key":"CqgDGHhPUi"},{"type":"text","value":" method from Xarray.","position":{"start":{"line":1,"column":1},"end":{"line":1,"column":1}},"key":"HbFvtfQ1y0"}],"key":"mAoAUn2CVT"}],"key":"jx7fTav6CE"},{"type":"block","kind":"notebook-code","data":{"tags":[]},"children":[{"type":"code","lang":"python","executable":true,"value":"ds_mon_climo = ds_mon_crop.groupby('time.month').mean()","visibility":"show","key":"LCYolU37RN"},{"type":"output","id":"9M5uj4Rvi9a5HVO-cHVUF","data":[],"visibility":"show","key":"tzZBsIL2kZ"}],"visibility":"show","key":"hKM815ZSrD"},{"type":"block","kind":"notebook-content","children":[{"type":"heading","depth":2,"position":{"start":{"line":1,"column":1},"end":{"line":1,"column":1}},"children":[{"type":"text","value":"Calculate the SST anomaly","position":{"start":{"line":1,"column":1},"end":{"line":1,"column":1}},"key":"NNeLadeYWy"}],"identifier":"calculate-the-sst-anomaly","label":"Calculate the SST anomaly","html_id":"calculate-the-sst-anomaly","implicit":true,"key":"Q0wR3oaPfS"},{"type":"paragraph","position":{"start":{"line":2,"column":1},"end":{"line":2,"column":1}},"children":[{"type":"text","value":"After the climatology is determined, we subtract the climatology from the original data to get the anomaly.","position":{"start":{"line":2,"column":1},"end":{"line":2,"column":1}},"key":"NHpBFSXm7G"}],"key":"mAC5PtBdPC"}],"key":"yMzo1e1v1Q"},{"type":"block","kind":"notebook-code","data":{"tags":[]},"children":[{"type":"code","lang":"python","executable":true,"value":"ds_mon_anom = (ds_mon_crop.groupby('time.month')-ds_mon_climo).compute()","visibility":"show","key":"gHq9CxXX36"},{"type":"output","id":"HtYQf0eYT14U7rwqKp5qi","data":[],"visibility":"show","key":"QfRMhyuoT5"}],"visibility":"show","key":"BGF9tIrkOj"},{"type":"block","kind":"notebook-content","children":[{"type":"div","class":"admonition alert alert-success","children":[{"type":"paragraph","children":[{"type":"text","value":".compute()","key":"g7Hx7PEkIF"}],"key":"BhieWDwEvy"},{"type":"text","value":"Notice the `.compute()` method in the code above. The data of SST is only loaded chunk-by-chunk, cropped to the desired period, averaged in the group of months, and finally subtracted the climatology from the original data when we execute the `.compute()` line. All these tasks are now executed in the background with a distributed server assigning tasks to different CPUs.","key":"riyo08uuAG"}],"key":"eLNw0qjFiD"}],"key":"bLEh53Q8J0"},{"type":"block","kind":"notebook-code","data":{"tags":[]},"children":[{"type":"code","lang":"python","executable":true,"value":"ds_mon_anom","visibility":"show","key":"mJWuf4Lva8"},{"type":"output","id":"MQoKkSIZbGkVYOMntOrn8","data":[{"output_type":"execute_result","execution_count":10,"metadata":{},"data":{"text/plain":{"content":"<xarray.Dataset> Size: 100MB\nDimensions:  (time: 24, lat: 720, lon: 1440)\nCoordinates:\n  * time     (time) datetime64[ns] 192B 2019-01-01 2019-02-01 ... 2020-12-01\n  * lat      (lat) float32 3kB -89.88 -89.62 -89.38 -89.12 ... 89.38 89.62 89.88\n  * lon      (lon) float32 6kB 0.125 0.375 0.625 0.875 ... 359.4 359.6 359.9\n    month    (time) int64 192B 1 2 3 4 5 6 7 8 9 10 ... 3 4 5 6 7 8 9 10 11 12\nData variables:\n    sst      (time, lat, lon) float32 100MB 0.0 0.0 0.0 0.0 ... 0.0 0.0 0.0","content_type":"text/plain"},"text/html":{"content":"<div><svg style=\"position: absolute; width: 0; height: 0; overflow: hidden\">\n<defs>\n<symbol id=\"icon-database\" viewBox=\"0 0 32 32\">\n<path d=\"M16 0c-8.837 0-16 2.239-16 5v4c0 2.761 7.163 5 16 5s16-2.239 16-5v-4c0-2.761-7.163-5-16-5z\"></path>\n<path d=\"M16 17c-8.837 0-16-2.239-16-5v6c0 2.761 7.163 5 16 5s16-2.239 16-5v-6c0 2.761-7.163 5-16 5z\"></path>\n<path d=\"M16 26c-8.837 0-16-2.239-16-5v6c0 2.761 7.163 5 16 5s16-2.239 16-5v-6c0 2.761-7.163 5-16 5z\"></path>\n</symbol>\n<symbol id=\"icon-file-text2\" viewBox=\"0 0 32 32\">\n<path d=\"M28.681 7.159c-0.694-0.947-1.662-2.053-2.724-3.116s-2.169-2.030-3.116-2.724c-1.612-1.182-2.393-1.319-2.841-1.319h-15.5c-1.378 0-2.5 1.121-2.5 2.5v27c0 1.378 1.122 2.5 2.5 2.5h23c1.378 0 2.5-1.122 2.5-2.5v-19.5c0-0.448-0.137-1.23-1.319-2.841zM24.543 5.457c0.959 0.959 1.712 1.825 2.268 2.543h-4.811v-4.811c0.718 0.556 1.584 1.309 2.543 2.268zM28 29.5c0 0.271-0.229 0.5-0.5 0.5h-23c-0.271 0-0.5-0.229-0.5-0.5v-27c0-0.271 0.229-0.5 0.5-0.5 0 0 15.499-0 15.5 0v7c0 0.552 0.448 1 1 1h7v19.5z\"></path>\n<path d=\"M23 26h-14c-0.552 0-1-0.448-1-1s0.448-1 1-1h14c0.552 0 1 0.448 1 1s-0.448 1-1 1z\"></path>\n<path d=\"M23 22h-14c-0.552 0-1-0.448-1-1s0.448-1 1-1h14c0.552 0 1 0.448 1 1s-0.448 1-1 1z\"></path>\n<path d=\"M23 18h-14c-0.552 0-1-0.448-1-1s0.448-1 1-1h14c0.552 0 1 0.448 1 1s-0.448 1-1 1z\"></path>\n</symbol>\n</defs>\n</svg>\n<style>/* CSS stylesheet for displaying xarray objects in jupyterlab.\n *\n */\n\n:root {\n  --xr-font-color0: var(\n    --jp-content-font-color0,\n    var(--pst-color-text-base rgba(0, 0, 0, 1))\n  );\n  --xr-font-color2: var(\n    --jp-content-font-color2,\n    var(--pst-color-text-base, rgba(0, 0, 0, 0.54))\n  );\n  --xr-font-color3: var(\n    --jp-content-font-color3,\n    var(--pst-color-text-base, rgba(0, 0, 0, 0.38))\n  );\n  --xr-border-color: var(\n    --jp-border-color2,\n    hsl(from var(--pst-color-on-background, white) h s calc(l - 10))\n  );\n  --xr-disabled-color: var(\n    --jp-layout-color3,\n    hsl(from var(--pst-color-on-background, white) h s calc(l - 40))\n  );\n  --xr-background-color: var(\n    --jp-layout-color0,\n    var(--pst-color-on-background, white)\n  );\n  --xr-background-color-row-even: var(\n    --jp-layout-color1,\n    hsl(from var(--pst-color-on-background, white) h s calc(l - 5))\n  );\n  --xr-background-color-row-odd: var(\n    --jp-layout-color2,\n    hsl(from var(--pst-color-on-background, white) h s calc(l - 15))\n  );\n}\n\nhtml[theme=\"dark\"],\nhtml[data-theme=\"dark\"],\nbody[data-theme=\"dark\"],\nbody.vscode-dark {\n  --xr-font-color0: var(\n    --jp-content-font-color0,\n    var(--pst-color-text-base, rgba(255, 255, 255, 1))\n  );\n  --xr-font-color2: var(\n    --jp-content-font-color2,\n    var(--pst-color-text-base, rgba(255, 255, 255, 0.54))\n  );\n  --xr-font-color3: var(\n    --jp-content-font-color3,\n    var(--pst-color-text-base, rgba(255, 255, 255, 0.38))\n  );\n  --xr-border-color: var(\n    --jp-border-color2,\n    hsl(from var(--pst-color-on-background, #111111) h s calc(l + 10))\n  );\n  --xr-disabled-color: var(\n    --jp-layout-color3,\n    hsl(from var(--pst-color-on-background, #111111) h s calc(l + 40))\n  );\n  --xr-background-color: var(\n    --jp-layout-color0,\n    var(--pst-color-on-background, #111111)\n  );\n  --xr-background-color-row-even: var(\n    --jp-layout-color1,\n    hsl(from var(--pst-color-on-background, #111111) h s calc(l + 5))\n  );\n  --xr-background-color-row-odd: var(\n    --jp-layout-color2,\n    hsl(from var(--pst-color-on-background, #111111) h s calc(l + 15))\n  );\n}\n\n.xr-wrap {\n  display: block !important;\n  min-width: 300px;\n  max-width: 700px;\n}\n\n.xr-text-repr-fallback {\n  /* fallback to plain text repr when CSS is not injected (untrusted notebook) */\n  display: none;\n}\n\n.xr-header {\n  padding-top: 6px;\n  padding-bottom: 6px;\n  margin-bottom: 4px;\n  border-bottom: solid 1px var(--xr-border-color);\n}\n\n.xr-header > div,\n.xr-header > ul {\n  display: inline;\n  margin-top: 0;\n  margin-bottom: 0;\n}\n\n.xr-obj-type,\n.xr-array-name {\n  margin-left: 2px;\n  margin-right: 10px;\n}\n\n.xr-obj-type {\n  color: var(--xr-font-color2);\n}\n\n.xr-sections {\n  padding-left: 0 !important;\n  display: grid;\n  grid-template-columns: 150px auto auto 1fr 0 20px 0 20px;\n}\n\n.xr-section-item {\n  display: contents;\n}\n\n.xr-section-item input {\n  display: inline-block;\n  opacity: 0;\n  height: 0;\n}\n\n.xr-section-item input + label {\n  color: var(--xr-disabled-color);\n  border: 2px solid transparent !important;\n}\n\n.xr-section-item input:enabled + label {\n  cursor: pointer;\n  color: var(--xr-font-color2);\n}\n\n.xr-section-item input:focus + label {\n  border: 2px solid var(--xr-font-color0) !important;\n}\n\n.xr-section-item input:enabled + label:hover {\n  color: var(--xr-font-color0);\n}\n\n.xr-section-summary {\n  grid-column: 1;\n  color: var(--xr-font-color2);\n  font-weight: 500;\n}\n\n.xr-section-summary > span {\n  display: inline-block;\n  padding-left: 0.5em;\n}\n\n.xr-section-summary-in:disabled + label {\n  color: var(--xr-font-color2);\n}\n\n.xr-section-summary-in + label:before {\n  display: inline-block;\n  content: \"►\";\n  font-size: 11px;\n  width: 15px;\n  text-align: center;\n}\n\n.xr-section-summary-in:disabled + label:before {\n  color: var(--xr-disabled-color);\n}\n\n.xr-section-summary-in:checked + label:before {\n  content: \"▼\";\n}\n\n.xr-section-summary-in:checked + label > span {\n  display: none;\n}\n\n.xr-section-summary,\n.xr-section-inline-details {\n  padding-top: 4px;\n  padding-bottom: 4px;\n}\n\n.xr-section-inline-details {\n  grid-column: 2 / -1;\n}\n\n.xr-section-details {\n  display: none;\n  grid-column: 1 / -1;\n  margin-bottom: 5px;\n}\n\n.xr-section-summary-in:checked ~ .xr-section-details {\n  display: contents;\n}\n\n.xr-array-wrap {\n  grid-column: 1 / -1;\n  display: grid;\n  grid-template-columns: 20px auto;\n}\n\n.xr-array-wrap > label {\n  grid-column: 1;\n  vertical-align: top;\n}\n\n.xr-preview {\n  color: var(--xr-font-color3);\n}\n\n.xr-array-preview,\n.xr-array-data {\n  padding: 0 5px !important;\n  grid-column: 2;\n}\n\n.xr-array-data,\n.xr-array-in:checked ~ .xr-array-preview {\n  display: none;\n}\n\n.xr-array-in:checked ~ .xr-array-data,\n.xr-array-preview {\n  display: inline-block;\n}\n\n.xr-dim-list {\n  display: inline-block !important;\n  list-style: none;\n  padding: 0 !important;\n  margin: 0;\n}\n\n.xr-dim-list li {\n  display: inline-block;\n  padding: 0;\n  margin: 0;\n}\n\n.xr-dim-list:before {\n  content: \"(\";\n}\n\n.xr-dim-list:after {\n  content: \")\";\n}\n\n.xr-dim-list li:not(:last-child):after {\n  content: \",\";\n  padding-right: 5px;\n}\n\n.xr-has-index {\n  font-weight: bold;\n}\n\n.xr-var-list,\n.xr-var-item {\n  display: contents;\n}\n\n.xr-var-item > div,\n.xr-var-item label,\n.xr-var-item > .xr-var-name span {\n  background-color: var(--xr-background-color-row-even);\n  border-color: var(--xr-background-color-row-odd);\n  margin-bottom: 0;\n  padding-top: 2px;\n}\n\n.xr-var-item > .xr-var-name:hover span {\n  padding-right: 5px;\n}\n\n.xr-var-list > li:nth-child(odd) > div,\n.xr-var-list > li:nth-child(odd) > label,\n.xr-var-list > li:nth-child(odd) > .xr-var-name span {\n  background-color: var(--xr-background-color-row-odd);\n  border-color: var(--xr-background-color-row-even);\n}\n\n.xr-var-name {\n  grid-column: 1;\n}\n\n.xr-var-dims {\n  grid-column: 2;\n}\n\n.xr-var-dtype {\n  grid-column: 3;\n  text-align: right;\n  color: var(--xr-font-color2);\n}\n\n.xr-var-preview {\n  grid-column: 4;\n}\n\n.xr-index-preview {\n  grid-column: 2 / 5;\n  color: var(--xr-font-color2);\n}\n\n.xr-var-name,\n.xr-var-dims,\n.xr-var-dtype,\n.xr-preview,\n.xr-attrs dt {\n  white-space: nowrap;\n  overflow: hidden;\n  text-overflow: ellipsis;\n  padding-right: 10px;\n}\n\n.xr-var-name:hover,\n.xr-var-dims:hover,\n.xr-var-dtype:hover,\n.xr-attrs dt:hover {\n  overflow: visible;\n  width: auto;\n  z-index: 1;\n}\n\n.xr-var-attrs,\n.xr-var-data,\n.xr-index-data {\n  display: none;\n  border-top: 2px dotted var(--xr-background-color);\n  padding-bottom: 20px !important;\n  padding-top: 10px !important;\n}\n\n.xr-var-attrs-in + label,\n.xr-var-data-in + label,\n.xr-index-data-in + label {\n  padding: 0 1px;\n}\n\n.xr-var-attrs-in:checked ~ .xr-var-attrs,\n.xr-var-data-in:checked ~ .xr-var-data,\n.xr-index-data-in:checked ~ .xr-index-data {\n  display: block;\n}\n\n.xr-var-data > table {\n  float: right;\n}\n\n.xr-var-data > pre,\n.xr-index-data > pre,\n.xr-var-data > table > tbody > tr {\n  background-color: transparent !important;\n}\n\n.xr-var-name span,\n.xr-var-data,\n.xr-index-name div,\n.xr-index-data,\n.xr-attrs {\n  padding-left: 25px !important;\n}\n\n.xr-attrs,\n.xr-var-attrs,\n.xr-var-data,\n.xr-index-data {\n  grid-column: 1 / -1;\n}\n\ndl.xr-attrs {\n  padding: 0;\n  margin: 0;\n  display: grid;\n  grid-template-columns: 125px auto;\n}\n\n.xr-attrs dt,\n.xr-attrs dd {\n  padding: 0;\n  margin: 0;\n  float: left;\n  padding-right: 10px;\n  width: auto;\n}\n\n.xr-attrs dt {\n  font-weight: normal;\n  grid-column: 1;\n}\n\n.xr-attrs dt:hover span {\n  display: inline-block;\n  background: var(--xr-background-color);\n  padding-right: 10px;\n}\n\n.xr-attrs dd {\n  grid-column: 2;\n  white-space: pre-wrap;\n  word-break: break-all;\n}\n\n.xr-icon-database,\n.xr-icon-file-text2,\n.xr-no-icon {\n  display: inline-block;\n  vertical-align: middle;\n  width: 1em;\n  height: 1.5em !important;\n  stroke-width: 0;\n  stroke: currentColor;\n  fill: currentColor;\n}\n\n.xr-var-attrs-in:checked + label > .xr-icon-file-text2,\n.xr-var-data-in:checked + label > .xr-icon-database,\n.xr-index-data-in:checked + label > .xr-icon-database {\n  color: var(--xr-font-color0);\n  filter: drop-shadow(1px 1px 5px var(--xr-font-color2));\n  stroke-width: 0.8px;\n}\n</style><pre class='xr-text-repr-fallback'>&lt;xarray.Dataset&gt; Size: 100MB\nDimensions:  (time: 24, lat: 720, lon: 1440)\nCoordinates:\n  * time     (time) datetime64[ns] 192B 2019-01-01 2019-02-01 ... 2020-12-01\n  * lat      (lat) float32 3kB -89.88 -89.62 -89.38 -89.12 ... 89.38 89.62 89.88\n  * lon      (lon) float32 6kB 0.125 0.375 0.625 0.875 ... 359.4 359.6 359.9\n    month    (time) int64 192B 1 2 3 4 5 6 7 8 9 10 ... 3 4 5 6 7 8 9 10 11 12\nData variables:\n    sst      (time, lat, lon) float32 100MB 0.0 0.0 0.0 0.0 ... 0.0 0.0 0.0</pre><div class='xr-wrap' style='display:none'><div class='xr-header'><div class='xr-obj-type'>xarray.Dataset</div></div><ul class='xr-sections'><li class='xr-section-item'><input id='section-677f06a0-1532-4c2e-be08-dcf9ee3f8995' class='xr-section-summary-in' type='checkbox' disabled ><label for='section-677f06a0-1532-4c2e-be08-dcf9ee3f8995' class='xr-section-summary'  title='Expand/collapse section'>Dimensions:</label><div class='xr-section-inline-details'><ul class='xr-dim-list'><li><span class='xr-has-index'>time</span>: 24</li><li><span class='xr-has-index'>lat</span>: 720</li><li><span class='xr-has-index'>lon</span>: 1440</li></ul></div><div class='xr-section-details'></div></li><li class='xr-section-item'><input id='section-fed4b75b-a509-4da7-947f-8afb1e053e5d' class='xr-section-summary-in' type='checkbox'  checked><label for='section-fed4b75b-a509-4da7-947f-8afb1e053e5d' class='xr-section-summary' >Coordinates: <span>(4)</span></label><div class='xr-section-inline-details'></div><div class='xr-section-details'><ul class='xr-var-list'><li class='xr-var-item'><div class='xr-var-name'><span class='xr-has-index'>time</span></div><div class='xr-var-dims'>(time)</div><div class='xr-var-dtype'>datetime64[ns]</div><div class='xr-var-preview xr-preview'>2019-01-01 ... 2020-12-01</div><input id='attrs-c2fc9a2e-3b9e-4ab9-81d1-d97757ce6a19' class='xr-var-attrs-in' type='checkbox' ><label for='attrs-c2fc9a2e-3b9e-4ab9-81d1-d97757ce6a19' title='Show/Hide attributes'><svg class='icon xr-icon-file-text2'><use xlink:href='#icon-file-text2'></use></svg></label><input id='data-4e840aa0-ae03-4c89-ab33-7f375812d72b' class='xr-var-data-in' type='checkbox'><label for='data-4e840aa0-ae03-4c89-ab33-7f375812d72b' title='Show/Hide data repr'><svg class='icon xr-icon-database'><use xlink:href='#icon-database'></use></svg></label><div class='xr-var-attrs'><dl class='xr-attrs'><dt><span>long_name :</span></dt><dd>Time</dd><dt><span>delta_t :</span></dt><dd>0000-01-00 00:00:00</dd><dt><span>avg_period :</span></dt><dd>0000-01-00 00:00:00</dd><dt><span>axis :</span></dt><dd>T</dd><dt><span>actual_range :</span></dt><dd>[66352.0, 82361.0]</dd><dt><span>_ChunkSizes :</span></dt><dd>512</dd></dl></div><div class='xr-var-data'><pre>array([&#x27;2019-01-01T00:00:00.000000000&#x27;, &#x27;2019-02-01T00:00:00.000000000&#x27;,\n       &#x27;2019-03-01T00:00:00.000000000&#x27;, &#x27;2019-04-01T00:00:00.000000000&#x27;,\n       &#x27;2019-05-01T00:00:00.000000000&#x27;, &#x27;2019-06-01T00:00:00.000000000&#x27;,\n       &#x27;2019-07-01T00:00:00.000000000&#x27;, &#x27;2019-08-01T00:00:00.000000000&#x27;,\n       &#x27;2019-09-01T00:00:00.000000000&#x27;, &#x27;2019-10-01T00:00:00.000000000&#x27;,\n       &#x27;2019-11-01T00:00:00.000000000&#x27;, &#x27;2019-12-01T00:00:00.000000000&#x27;,\n       &#x27;2020-01-01T00:00:00.000000000&#x27;, &#x27;2020-02-01T00:00:00.000000000&#x27;,\n       &#x27;2020-03-01T00:00:00.000000000&#x27;, &#x27;2020-04-01T00:00:00.000000000&#x27;,\n       &#x27;2020-05-01T00:00:00.000000000&#x27;, &#x27;2020-06-01T00:00:00.000000000&#x27;,\n       &#x27;2020-07-01T00:00:00.000000000&#x27;, &#x27;2020-08-01T00:00:00.000000000&#x27;,\n       &#x27;2020-09-01T00:00:00.000000000&#x27;, &#x27;2020-10-01T00:00:00.000000000&#x27;,\n       &#x27;2020-11-01T00:00:00.000000000&#x27;, &#x27;2020-12-01T00:00:00.000000000&#x27;],\n      dtype=&#x27;datetime64[ns]&#x27;)</pre></div></li><li class='xr-var-item'><div class='xr-var-name'><span class='xr-has-index'>lat</span></div><div class='xr-var-dims'>(lat)</div><div class='xr-var-dtype'>float32</div><div class='xr-var-preview xr-preview'>-89.88 -89.62 ... 89.62 89.88</div><input id='attrs-e4671b29-a810-4c5c-9236-359c37b3903e' class='xr-var-attrs-in' type='checkbox' ><label for='attrs-e4671b29-a810-4c5c-9236-359c37b3903e' title='Show/Hide attributes'><svg class='icon xr-icon-file-text2'><use xlink:href='#icon-file-text2'></use></svg></label><input id='data-fcb0d708-226c-4cc7-805d-09f4e8164888' class='xr-var-data-in' type='checkbox'><label for='data-fcb0d708-226c-4cc7-805d-09f4e8164888' title='Show/Hide data repr'><svg class='icon xr-icon-database'><use xlink:href='#icon-database'></use></svg></label><div class='xr-var-attrs'><dl class='xr-attrs'><dt><span>long_name :</span></dt><dd>Latitude</dd><dt><span>standard_name :</span></dt><dd>latitude</dd><dt><span>units :</span></dt><dd>degrees_north</dd><dt><span>actual_range :</span></dt><dd>[-89.875, 89.875]</dd><dt><span>axis :</span></dt><dd>Y</dd></dl></div><div class='xr-var-data'><pre>array([-89.875, -89.625, -89.375, ...,  89.375,  89.625,  89.875],\n      shape=(720,), dtype=float32)</pre></div></li><li class='xr-var-item'><div class='xr-var-name'><span class='xr-has-index'>lon</span></div><div class='xr-var-dims'>(lon)</div><div class='xr-var-dtype'>float32</div><div class='xr-var-preview xr-preview'>0.125 0.375 0.625 ... 359.6 359.9</div><input id='attrs-31efc9aa-825e-430d-9467-cc0af4906783' class='xr-var-attrs-in' type='checkbox' ><label for='attrs-31efc9aa-825e-430d-9467-cc0af4906783' title='Show/Hide attributes'><svg class='icon xr-icon-file-text2'><use xlink:href='#icon-file-text2'></use></svg></label><input id='data-cd1b9e18-be39-45fe-95de-5a37f4a24f80' class='xr-var-data-in' type='checkbox'><label for='data-cd1b9e18-be39-45fe-95de-5a37f4a24f80' title='Show/Hide data repr'><svg class='icon xr-icon-database'><use xlink:href='#icon-database'></use></svg></label><div class='xr-var-attrs'><dl class='xr-attrs'><dt><span>long_name :</span></dt><dd>Longitude</dd><dt><span>standard_name :</span></dt><dd>longitude</dd><dt><span>units :</span></dt><dd>degrees_east</dd><dt><span>actual_range :</span></dt><dd>[0.125, 359.875]</dd><dt><span>axis :</span></dt><dd>X</dd></dl></div><div class='xr-var-data'><pre>array([1.25000e-01, 3.75000e-01, 6.25000e-01, ..., 3.59375e+02, 3.59625e+02,\n       3.59875e+02], shape=(1440,), dtype=float32)</pre></div></li><li class='xr-var-item'><div class='xr-var-name'><span>month</span></div><div class='xr-var-dims'>(time)</div><div class='xr-var-dtype'>int64</div><div class='xr-var-preview xr-preview'>1 2 3 4 5 6 7 ... 6 7 8 9 10 11 12</div><input id='attrs-92dec9a2-73f0-4c11-a6a2-cb82e81cbfc5' class='xr-var-attrs-in' type='checkbox' disabled><label for='attrs-92dec9a2-73f0-4c11-a6a2-cb82e81cbfc5' title='Show/Hide attributes'><svg class='icon xr-icon-file-text2'><use xlink:href='#icon-file-text2'></use></svg></label><input id='data-55f43c1d-d481-430a-a08a-bbc16dae93c1' class='xr-var-data-in' type='checkbox'><label for='data-55f43c1d-d481-430a-a08a-bbc16dae93c1' title='Show/Hide data repr'><svg class='icon xr-icon-database'><use xlink:href='#icon-database'></use></svg></label><div class='xr-var-attrs'><dl class='xr-attrs'></dl></div><div class='xr-var-data'><pre>array([ 1,  2,  3,  4,  5,  6,  7,  8,  9, 10, 11, 12,  1,  2,  3,  4,  5,\n        6,  7,  8,  9, 10, 11, 12])</pre></div></li></ul></div></li><li class='xr-section-item'><input id='section-57c09ee2-bc9a-4cfb-9f69-d7ac95ac5750' class='xr-section-summary-in' type='checkbox'  checked><label for='section-57c09ee2-bc9a-4cfb-9f69-d7ac95ac5750' class='xr-section-summary' >Data variables: <span>(1)</span></label><div class='xr-section-inline-details'></div><div class='xr-section-details'><ul class='xr-var-list'><li class='xr-var-item'><div class='xr-var-name'><span>sst</span></div><div class='xr-var-dims'>(time, lat, lon)</div><div class='xr-var-dtype'>float32</div><div class='xr-var-preview xr-preview'>0.0 0.0 0.0 0.0 ... 0.0 0.0 0.0</div><input id='attrs-b0a9d725-4c26-4043-9308-3a6b51d6968a' class='xr-var-attrs-in' type='checkbox' disabled><label for='attrs-b0a9d725-4c26-4043-9308-3a6b51d6968a' title='Show/Hide attributes'><svg class='icon xr-icon-file-text2'><use xlink:href='#icon-file-text2'></use></svg></label><input id='data-ead823e5-4bbe-4999-9bf1-fbee02849c68' class='xr-var-data-in' type='checkbox'><label for='data-ead823e5-4bbe-4999-9bf1-fbee02849c68' title='Show/Hide data repr'><svg class='icon xr-icon-database'><use xlink:href='#icon-database'></use></svg></label><div class='xr-var-attrs'><dl class='xr-attrs'></dl></div><div class='xr-var-data'><pre>array([[[ 0.        ,  0.        ,  0.        , ...,  0.        ,\n          0.        ,  0.        ],\n        [ 0.        ,  0.        ,  0.        , ...,  0.        ,\n          0.        ,  0.        ],\n        [ 0.        ,  0.        ,  0.        , ...,  0.        ,\n          0.        ,  0.        ],\n        ...,\n        [ 0.00532258,  0.00532258,  0.00693548, ...,  0.00596774,\n          0.00629032,  0.00516129],\n        [ 0.00241935,  0.00274193,  0.00177419, ...,  0.00370967,\n          0.00274193,  0.00290322],\n        [ 0.        ,  0.        ,  0.        , ...,  0.        ,\n          0.        ,  0.        ]],\n\n       [[ 0.        ,  0.        ,  0.        , ...,  0.        ,\n          0.        ,  0.        ],\n        [ 0.        ,  0.        ,  0.        , ...,  0.        ,\n          0.        ,  0.        ],\n        [ 0.        ,  0.        ,  0.        , ...,  0.        ,\n          0.        ,  0.        ],\n...\n        [ 0.02583337,  0.02333331,  0.02299988, ...,  0.01999998,\n          0.02166665,  0.02499998],\n        [ 0.01749992,  0.01249993,  0.01049995, ...,  0.01033342,\n          0.0126667 ,  0.01599991],\n        [ 0.        ,  0.        ,  0.00849998, ...,  0.00516665,\n          0.        ,  0.        ]],\n\n       [[ 0.        ,  0.        ,  0.        , ...,  0.        ,\n          0.        ,  0.        ],\n        [ 0.        ,  0.        ,  0.        , ...,  0.        ,\n          0.        ,  0.        ],\n        [ 0.        ,  0.        ,  0.        , ...,  0.        ,\n          0.        ,  0.        ],\n        ...,\n        [ 0.00451612,  0.00467741,  0.00580645, ...,  0.00612903,\n          0.00564516,  0.00419354],\n        [ 0.00016129,  0.00177419,  0.00419354, ...,  0.00403225,\n          0.00225806, -0.00096774],\n        [ 0.        ,  0.        ,  0.        , ...,  0.        ,\n          0.        ,  0.        ]]], shape=(24, 720, 1440), dtype=float32)</pre></div></li></ul></div></li><li class='xr-section-item'><input id='section-3b86e04c-bf57-43f0-a9fb-7f4f358661ea' class='xr-section-summary-in' type='checkbox'  ><label for='section-3b86e04c-bf57-43f0-a9fb-7f4f358661ea' class='xr-section-summary' >Indexes: <span>(3)</span></label><div class='xr-section-inline-details'></div><div class='xr-section-details'><ul class='xr-var-list'><li class='xr-var-item'><div class='xr-index-name'><div>time</div></div><div class='xr-index-preview'>PandasIndex</div><input type='checkbox' disabled/><label></label><input id='index-4dc52bca-2a7e-4206-83d6-df3dfdb23f7d' class='xr-index-data-in' type='checkbox'/><label for='index-4dc52bca-2a7e-4206-83d6-df3dfdb23f7d' title='Show/Hide index repr'><svg class='icon xr-icon-database'><use xlink:href='#icon-database'></use></svg></label><div class='xr-index-data'><pre>PandasIndex(DatetimeIndex([&#x27;2019-01-01&#x27;, &#x27;2019-02-01&#x27;, &#x27;2019-03-01&#x27;, &#x27;2019-04-01&#x27;,\n               &#x27;2019-05-01&#x27;, &#x27;2019-06-01&#x27;, &#x27;2019-07-01&#x27;, &#x27;2019-08-01&#x27;,\n               &#x27;2019-09-01&#x27;, &#x27;2019-10-01&#x27;, &#x27;2019-11-01&#x27;, &#x27;2019-12-01&#x27;,\n               &#x27;2020-01-01&#x27;, &#x27;2020-02-01&#x27;, &#x27;2020-03-01&#x27;, &#x27;2020-04-01&#x27;,\n               &#x27;2020-05-01&#x27;, &#x27;2020-06-01&#x27;, &#x27;2020-07-01&#x27;, &#x27;2020-08-01&#x27;,\n               &#x27;2020-09-01&#x27;, &#x27;2020-10-01&#x27;, &#x27;2020-11-01&#x27;, &#x27;2020-12-01&#x27;],\n              dtype=&#x27;datetime64[ns]&#x27;, name=&#x27;time&#x27;, freq=None))</pre></div></li><li class='xr-var-item'><div class='xr-index-name'><div>lat</div></div><div class='xr-index-preview'>PandasIndex</div><input type='checkbox' disabled/><label></label><input id='index-4cc291eb-490a-4387-b92f-1e586adfb87f' class='xr-index-data-in' type='checkbox'/><label for='index-4cc291eb-490a-4387-b92f-1e586adfb87f' title='Show/Hide index repr'><svg class='icon xr-icon-database'><use xlink:href='#icon-database'></use></svg></label><div class='xr-index-data'><pre>PandasIndex(Index([-89.875, -89.625, -89.375, -89.125, -88.875, -88.625, -88.375, -88.125,\n       -87.875, -87.625,\n       ...\n        87.625,  87.875,  88.125,  88.375,  88.625,  88.875,  89.125,  89.375,\n        89.625,  89.875],\n      dtype=&#x27;float32&#x27;, name=&#x27;lat&#x27;, length=720))</pre></div></li><li class='xr-var-item'><div class='xr-index-name'><div>lon</div></div><div class='xr-index-preview'>PandasIndex</div><input type='checkbox' disabled/><label></label><input id='index-a32c4311-330e-46ed-8902-53ef31cb6e8b' class='xr-index-data-in' type='checkbox'/><label for='index-a32c4311-330e-46ed-8902-53ef31cb6e8b' title='Show/Hide index repr'><svg class='icon xr-icon-database'><use xlink:href='#icon-database'></use></svg></label><div class='xr-index-data'><pre>PandasIndex(Index([  0.125,   0.375,   0.625,   0.875,   1.125,   1.375,   1.625,   1.875,\n         2.125,   2.375,\n       ...\n       357.625, 357.875, 358.125, 358.375, 358.625, 358.875, 359.125, 359.375,\n       359.625, 359.875],\n      dtype=&#x27;float32&#x27;, name=&#x27;lon&#x27;, length=1440))</pre></div></li></ul></div></li><li class='xr-section-item'><input id='section-6fcb2bd3-9153-4518-b101-a0f8728df76a' class='xr-section-summary-in' type='checkbox' disabled ><label for='section-6fcb2bd3-9153-4518-b101-a0f8728df76a' class='xr-section-summary'  title='Expand/collapse section'>Attributes: <span>(0)</span></label><div class='xr-section-inline-details'></div><div class='xr-section-details'><dl class='xr-attrs'></dl></div></li></ul></div></div>","content_type":"text/html"}}}],"visibility":"show","key":"cWnCQosktH"}],"visibility":"show","key":"lrnPJFACrc"},{"type":"block","kind":"notebook-content","children":[{"type":"heading","depth":2,"position":{"start":{"line":1,"column":1},"end":{"line":1,"column":1}},"children":[{"type":"text","value":"Determine the SST threshold based on the anomaly","position":{"start":{"line":1,"column":1},"end":{"line":1,"column":1}},"key":"pMAXyjyO05"}],"identifier":"determine-the-sst-threshold-based-on-the-anomaly","label":"Determine the SST threshold based on the anomaly","html_id":"determine-the-sst-threshold-based-on-the-anomaly","implicit":true,"key":"kuFRR1Ys44"}],"key":"KgT0zXPlup"},{"type":"block","kind":"notebook-content","children":[{"type":"paragraph","position":{"start":{"line":1,"column":1},"end":{"line":2,"column":1}},"children":[{"type":"text","value":"Based on the ","position":{"start":{"line":1,"column":1},"end":{"line":1,"column":1}},"key":"hI1e39WMba"},{"type":"cite","url":"http://doi.org/10.1038/s41586-022-04573-9","position":{"start":{"line":1,"column":1},"end":{"line":1,"column":1}},"children":[{"type":"text","value":"Jacox et al., 2022","position":{"start":{"line":1,"column":1},"end":{"line":1,"column":1}},"key":"fD2Eajj03H"}],"kind":"narrative","label":"Jacox_2022","identifier":"http://doi.org/10.1038/s41586-022-04573-9","enumerator":"1","key":"li7qePHHjb"},{"type":"text","value":", the threshold is determined based on a three month window with the center month being the monthly threhold one need to determined (e.g. January threshold is determined by all December, January, Feburary SST anomalies).\nTherefore, the function below is written to perform the three months window percentile operation.","position":{"start":{"line":1,"column":1},"end":{"line":1,"column":1}},"key":"jRHua2Mugp"}],"key":"WMJGRL4WV7"}],"key":"DuDpiUez3P"},{"type":"block","kind":"notebook-code","data":{"tags":[]},"children":[{"type":"code","lang":"python","executable":true,"value":"########## Functions ######### \n# Function to calculate the 3 month rolling Quantile\ndef mj_3mon_quantile(da_data, mhw_threshold=90.):\n    \n    da_data_quantile = xr.DataArray(coords={'lon':da_data.lon,\n                                            'lat':da_data.lat,\n                                            'month':np.arange(1,13)},\n                                    dims = ['month','lat','lon'])\n\n    for i in range(1,13):\n        if i == 1:\n            mon_range = [12,1,2]\n        elif i == 12 :\n            mon_range = [11,12,1]\n        else:\n            mon_range = [i-1,i,i+1]\n\n        da_data_quantile[i-1,:,:] = (da_data\n                                 .where((da_data['time.month'] == mon_range[0])|\n                                        (da_data['time.month'] == mon_range[1])|\n                                        (da_data['time.month'] == mon_range[2]),drop=True)\n                                 .quantile(mhw_threshold*0.01, dim = 'time', skipna = True))\n\n    return da_data_quantile\n","visibility":"show","key":"nBMMyaew5F"},{"type":"output","id":"royvONma8ekB3VVh2Ihe0","data":[],"visibility":"show","key":"tno4MT25Ck"}],"visibility":"show","key":"QFtPFBQ5cR"},{"type":"block","kind":"notebook-code","data":{"tags":[]},"children":[{"type":"code","lang":"python","executable":true,"value":"%time da_mon_quantile = mj_3mon_quantile(ds_mon_anom.sst, mhw_threshold=90)","visibility":"show","key":"QJFs7b2Tp4"},{"type":"output","id":"QmFEUIwkUG48vVXusfrbr","data":[{"output_type":"stream","name":"stdout","text":"CPU times: user 10min 19s, sys: 1.07 s, total: 10min 20s\nWall time: 10min 19s\n"}],"visibility":"show","key":"fwnQcOX11M"}],"visibility":"show","key":"rEIt24XTUq"},{"type":"block","kind":"notebook-content","children":[{"type":"div","class":"admonition alert alert-info","children":[{"type":"paragraph","children":[{"type":"text","value":"Tip","key":"uUVcmrevEt"}],"key":"WyYoQ01Y4l"},{"type":"text","value":"The `%time` command is jupyter cell magic to time the one-liner cell operation. It provides a great way to find the bottleneck of your data processing steps.","key":"HiMArmgM8S"}],"key":"wOMd6jdxaU"}],"key":"d6krtiRt4X"},{"type":"block","kind":"notebook-content","children":[{"type":"paragraph","position":{"start":{"line":1,"column":1},"end":{"line":1,"column":1}},"children":[{"type":"text","value":"The determined threshold value of each grid of each month is shown below","position":{"start":{"line":1,"column":1},"end":{"line":1,"column":1}},"key":"yYzXLVjMUp"}],"key":"moS1NxnkvT"}],"key":"Oc3jJHyc30"},{"type":"block","kind":"notebook-code","data":{"tags":[]},"children":[{"type":"code","lang":"python","executable":true,"value":"da_mon_quantile.isel(month=0).plot(vmin=0,vmax=3)","visibility":"show","key":"u3HhjjrGE6"},{"type":"output","id":"D_SMnWl5jJgVs_0yw52RW","data":[{"output_type":"display_data","metadata":{},"data":{"text/plain":{"content":"<Figure size 640x480 with 2 Axes>","content_type":"text/plain"},"image/png":{"content_type":"image/png","hash":"f971427b535224ffca66c1d6ad0a6872","path":"/marine-heatwave-cookbook/build/f971427b535224ffca66c1d6ad0a6872.png"}}}],"visibility":"show","key":"MUpTiynWN1"}],"visibility":"show","key":"xBAUd5RXXA"},{"type":"block","kind":"notebook-content","children":[{"type":"heading","depth":2,"position":{"start":{"line":1,"column":1},"end":{"line":1,"column":1}},"children":[{"type":"text","value":"Identify the marine heatwaves based on threshold","position":{"start":{"line":1,"column":1},"end":{"line":1,"column":1}},"key":"m7ZrRZyYTS"}],"identifier":"identify-the-marine-heatwaves-based-on-threshold","label":"Identify the marine heatwaves based on threshold","html_id":"identify-the-marine-heatwaves-based-on-threshold","implicit":true,"key":"RBxHx2GCJJ"},{"type":"paragraph","position":{"start":{"line":2,"column":1},"end":{"line":2,"column":1}},"children":[{"type":"text","value":"The figure below shows the original SST anomaly value for the first month.","position":{"start":{"line":2,"column":1},"end":{"line":2,"column":1}},"key":"Tq9iLqcfmD"}],"key":"gUGCuY5D6h"}],"key":"PbuHNu9U9d"},{"type":"block","kind":"notebook-code","data":{"tags":[]},"children":[{"type":"code","lang":"python","executable":true,"value":"ds_mon_anom.sst.isel(time=0).plot(vmin=0,vmax=3)","visibility":"show","key":"qdlhqJtvVt"},{"type":"output","id":"oWjSvVq3M2udFkhfbTLeh","data":[{"output_type":"display_data","metadata":{},"data":{"text/plain":{"content":"<Figure size 640x480 with 2 Axes>","content_type":"text/plain"},"image/png":{"content_type":"image/png","hash":"4c40f4fceee531426cfd100a57e7c0ee","path":"/marine-heatwave-cookbook/build/4c40f4fceee531426cfd100a57e7c0ee.png"}}}],"visibility":"show","key":"CCCrXR8Xnr"}],"visibility":"show","key":"mHzK6uHegX"},{"type":"block","kind":"notebook-content","children":[{"type":"paragraph","position":{"start":{"line":1,"column":1},"end":{"line":1,"column":1}},"children":[{"type":"text","value":"To identify the marine heatwaves based on the monthly threshold, we use the ","position":{"start":{"line":1,"column":1},"end":{"line":1,"column":1}},"key":"kOCzylCjeE"},{"type":"inlineCode","value":"where","position":{"start":{"line":1,"column":1},"end":{"line":1,"column":1}},"key":"XJw7WH7evK"},{"type":"text","value":" method to find the monthly marine heatwaves with the grid that has SST anomaly below the threshold to be masked as Not-a-Number.","position":{"start":{"line":1,"column":1},"end":{"line":1,"column":1}},"key":"PIEry3zWEp"}],"key":"gbIF2oqcPF"}],"key":"mdwl2AOhq7"},{"type":"block","kind":"notebook-code","data":{"tags":[]},"children":[{"type":"code","lang":"python","executable":true,"value":"da_mhw = ds_mon_anom.sst.where(ds_mon_anom.sst.groupby('time.month')>da_mon_quantile)","visibility":"show","key":"Zw9KXjegou"},{"type":"output","id":"wTKKmPTSZGsOs5E-NwQVL","data":[],"visibility":"show","key":"dBrffkDbEu"}],"visibility":"show","key":"IxloXilQwi"},{"type":"block","kind":"notebook-content","data":{"tags":[]},"children":[{"type":"paragraph","position":{"start":{"line":1,"column":1},"end":{"line":1,"column":1}},"children":[{"type":"text","value":"The figure below shows the SST anomalous values that are above the monthly thresholds for the first months.","position":{"start":{"line":1,"column":1},"end":{"line":1,"column":1}},"key":"daQoOGfYii"}],"key":"rtZYbS3EBj"}],"visibility":"show","key":"c6ghw7TSjE"},{"type":"block","kind":"notebook-code","data":{"tags":[]},"children":[{"type":"code","lang":"python","executable":true,"value":"da_mhw.isel(time=0).plot(vmin=0,vmax=3)","visibility":"show","key":"K0H5sEfMGF"},{"type":"output","id":"zh_7L4N0FG5wE1oe_Jgkp","data":[{"output_type":"display_data","metadata":{},"data":{"text/plain":{"content":"<Figure size 640x480 with 2 Axes>","content_type":"text/plain"},"image/png":{"content_type":"image/png","hash":"b5b6de2b5d111b33c3fffe6a956b8374","path":"/marine-heatwave-cookbook/build/b5b6de2b5d111b33c3fffe6a956b8374.png"}}}],"visibility":"show","key":"zMtX6hjn3H"}],"visibility":"show","key":"YafkhaYcE0"},{"type":"block","kind":"notebook-content","children":[{"type":"heading","depth":2,"position":{"start":{"line":1,"column":1},"end":{"line":1,"column":1}},"children":[{"type":"text","value":"Interactive plot","position":{"start":{"line":1,"column":1},"end":{"line":1,"column":1}},"key":"PsPUPrq6hL"}],"identifier":"interactive-plot","label":"Interactive plot","html_id":"interactive-plot","implicit":true,"key":"BIJgbKoNmS"},{"type":"paragraph","position":{"start":{"line":2,"column":1},"end":{"line":5,"column":1}},"children":[{"type":"text","value":"The interactive plot is a great tool for looking at a local changes through zoom in.\nPlotly provides a great interface for the user to also pin point the actual value at the point where they are interested in.\nThe only thing that need further data manipulation for using the plotly tool is to convert the Xarray DataArray to Pandas DataFrame.\nHowever, this can be easily achieved throught the method ","position":{"start":{"line":2,"column":1},"end":{"line":2,"column":1}},"key":"kBdmJxz0jI"},{"type":"inlineCode","value":".to_dataframe()","position":{"start":{"line":2,"column":1},"end":{"line":2,"column":1}},"key":"V2q5omAB8r"},{"type":"text","value":" provided by the Xarray package.","position":{"start":{"line":2,"column":1},"end":{"line":2,"column":1}},"key":"bPRR82cJHy"}],"key":"bFJMBDB9IP"}],"key":"YpTc2zDVx6"},{"type":"block","kind":"notebook-code","children":[{"type":"code","lang":"python","executable":true,"value":"dff = (da_mhw.isel(time=0)\n             .to_dataframe()\n             .reset_index()\n             .dropna()\n      )\n\ndff = dff.rename(columns={'sst':'MHW magnitude'})","key":"o4FrkMslQj"},{"type":"output","id":"crS90InXA2xKL3CO0gm82","data":[],"key":"amSJAPKPF1"}],"key":"jyFK8bcUwa"},{"type":"block","kind":"notebook-content","children":[{"type":"heading","depth":3,"position":{"start":{"line":1,"column":1},"end":{"line":1,"column":1}},"children":[{"type":"text","value":"Plotly setting","position":{"start":{"line":1,"column":1},"end":{"line":1,"column":1}},"key":"FAZT3gzGa1"}],"identifier":"plotly-setting","label":"Plotly setting","html_id":"plotly-setting","implicit":true,"key":"lKZnzESGdC"},{"type":"paragraph","position":{"start":{"line":2,"column":1},"end":{"line":2,"column":1}},"children":[{"type":"text","value":"After the DataFrame is created the plotly map can be created. Here, we are only using some simple options. More detail setups and options can be find on the ","position":{"start":{"line":2,"column":1},"end":{"line":2,"column":1}},"key":"wNr3YMwHK3"},{"type":"link","url":"https://plotly.com/python/scattermapbox/","position":{"start":{"line":2,"column":1},"end":{"line":2,"column":1}},"children":[{"type":"text","value":"Plotly documentation","position":{"start":{"line":2,"column":1},"end":{"line":2,"column":1}},"key":"M89gNt4iFn"}],"urlSource":"https://plotly.com/python/scattermapbox/","key":"Lay9E0B373"}],"key":"OECEfmK5JK"}],"key":"UJaS7e47N7"},{"type":"block","kind":"notebook-code","data":{"tags":[]},"children":[{"type":"code","lang":"python","executable":true,"value":"# Setup the scatter mapbox detail\ncenter = {'lat':38,'lon':-94}   # center of the map\nzoom = 2                        # zoom level of the map\nmarker_size = 8                 # marker size used on the map\nmapbox_style = 'carto-positron' # mapbox options\n\nfig = px.scatter_mapbox(dff,\n    lon = 'lon',\n    lat = 'lat',\n    color = 'MHW magnitude',\n    color_continuous_scale = 'orrd'\n)\n\nfig.update_layout(\n    mapbox={\n        'style': mapbox_style,\n        'center': center,\n        'zoom': zoom,\n    }\n)\n\n\n# Update the marker size using update_traces\nfig.update_traces(marker=dict(size=marker_size))\n","visibility":"show","key":"amL7inYJ9c"},{"type":"output","id":"tmPXqgloGV2dna2c1gNwM","data":[{"output_type":"display_data","metadata":{},"data":{"application/vnd.plotly.v1+json":{"content_type":"application/vnd.plotly.v1+json","hash":"cb5dd2919904302671a7f7c6b3d61924","path":"/marine-heatwave-cookbook/build/cb5dd2919904302671a7f7c6b3d61924.json"}}}],"visibility":"show","key":"a6yC4HCpzx"}],"visibility":"show","key":"EMwY4OAkAu"},{"type":"block","kind":"notebook-content","children":[{"type":"thematicBreak","position":{"start":{"line":1,"column":1},"end":{"line":1,"column":1}},"key":"HQ37L2Ooq7"}],"key":"k0zaq0nTxw"},{"type":"block","kind":"notebook-content","children":[{"type":"heading","depth":2,"position":{"start":{"line":1,"column":1},"end":{"line":1,"column":1}},"children":[{"type":"text","value":"Summary","position":{"start":{"line":1,"column":1},"end":{"line":1,"column":1}},"key":"WeDCTjrpAc"}],"identifier":"summary","label":"Summary","html_id":"summary","implicit":true,"key":"AxirJa5Iju"},{"type":"paragraph","position":{"start":{"line":2,"column":1},"end":{"line":3,"column":1}},"children":[{"type":"text","value":"Through this example, we demostrate how to lazily loaded a real world SST data from a OPeNDAP server and calculate the threshold that help us define the marine heatwave.\nBy using the threshold, we can find the marine heatwave in each month.","position":{"start":{"line":2,"column":1},"end":{"line":2,"column":1}},"key":"Zs71CAhcBA"}],"key":"M7pmyJ9fYB"},{"type":"heading","depth":3,"position":{"start":{"line":6,"column":1},"end":{"line":6,"column":1}},"children":[{"type":"text","value":"What’s next?","position":{"start":{"line":6,"column":1},"end":{"line":6,"column":1}},"key":"ccy9i8jYh1"}],"identifier":"whats-next","label":"What’s next?","html_id":"whats-next","implicit":true,"key":"mqj7PuF4vN"},{"type":"paragraph","position":{"start":{"line":7,"column":1},"end":{"line":7,"column":1}},"children":[{"type":"text","value":"A more interactive figures to view the marine heatwave will be added.","position":{"start":{"line":7,"column":1},"end":{"line":7,"column":1}},"key":"y8xvuiSAkk"}],"key":"rqna2oZfYn"}],"key":"KpMs2oqPRh"},{"type":"block","kind":"notebook-code","children":[{"type":"code","lang":"python","executable":true,"value":"","key":"tpo3BVXgjT"},{"type":"output","id":"z_axIyCfikHy9pq8QPxY-","data":[],"key":"sb7Fz9qPtv"}],"key":"MKwMsf2YLq"}],"key":"FkkENhHgLP"},"references":{"cite":{"order":["Jacox_2022"],"data":{"Jacox_2022":{"label":"Jacox_2022","enumerator":"1","doi":"10.1038/s41586-022-04573-9","html":"Jacox, M. G., Alexander, M. A., Amaya, D., Becker, E., Bograd, S. J., Brodie, S., Hazen, E. L., Pozo Buil, M., & Tommasi, D. (2022). Global seasonal forecasts of marine heatwaves. <i>Nature</i>, <i>604</i>(7906), 486–490. <a target=\"_blank\" rel=\"noreferrer\" href=\"https://doi.org/10.1038/s41586-022-04573-9\">10.1038/s41586-022-04573-9</a>","url":"https://doi.org/10.1038/s41586-022-04573-9"}}}},"footer":{"navigation":{"prev":{"title":"How to Cite This Cookbook","url":"/notebooks/how-to-cite","group":"Preamble"}}},"domain":"http://localhost:3000"}